{
   "name": "Mi 10T/10T Pro",
   "brand": "Xiaomi",
   "codename": "apollo",
   "xda_thread": "",
   "builds": {
      "gapps": [
         {
            "datetime": "1628803288",
            "filename": "dotOS-R-v5.1.3-apollo-GAPPS-20210812-2113.zip",
            "id": "cf77ad8d47dc433f76c036bf267d7b71",
            "romtype": "GAPPS",
            "size": "1598754638",
            "url": "https://downloads.droidontime.com/dot11/apollo/gapps/dotOS-R-v5.1.3-apollo-GAPPS-20210812-2113.zip",
            "version": "v5.1.3"
         }
      ],
      "vanilla": [
         {
            "datetime": "1628801443",
            "filename": "dotOS-R-v5.1.3-apollo-OFFICIAL-20210812-2008.zip",
            "id": "ee314bb6c16f44d7de0be839287d1f7e",
            "romtype": "OFFICIAL",
            "size": "1176188685",
            "url": "https://downloads.droidontime.com/dot11/apollo/vanilla/dotOS-R-v5.1.3-apollo-OFFICIAL-20210812-2008.zip",
            "version": "v5.1.3"
         }
      ]
   },
   "maintainers": [
      {
         "_id": "ejbtrd",
         "name": "ejbtrd",
         "url": "https://github.com/ejbtrd/"
      }
   ]
}
