{
   "name": "Redmi Note 4",
   "brand": "Xiaomi",
   "codename": "mido",
   "xda_thread": "https://forum.xda-developers.com/t/rom-android-11-dotos-5-0-1-redmi-note-4-official-mido-13-04-2021.4230293/",
   "builds": {
      "gapps": [
         {
            "datetime": "1618324744",
            "filename": "dotOS-R-v5.0.1-mido-GAPPS-20210413-1440.zip",
            "id": "6267513a9cf3c637ecbf14dbfc1e824a",
            "romtype": "GAPPS",
            "size": "1066454058",
            "url": "https://downloads.droidontime.com/dot11/mido/gapps/dotOS-R-v5.0.1-mido-GAPPS-20210413-1440.zip/",
            "version": "v5.0.1"
         }
      ],
      "vanilla": [
         {
            "datetime": "1618323916",
            "filename": "dotOS-R-v5.0.1-mido-OFFICIAL-20210413-1426.zip",
            "id": "1ff355ad59de57e40e0ae843be795c22",
            "romtype": "OFFICIAL",
            "size": "653272355",
            "url": "https://downloads.droidontime.com/dot11/mido/vanilla/dotOS-R-v5.0.1-mido-OFFICIAL-20210413-1426.zip",
            "version": "v5.0.1"
         }
      ]
   },
   "maintainers": [
      {
         "_id": "mohan",
         "name": "Mohan C M",
         "url": "https://github.com/mohancm"
      }
   ]
}
