{
   "name": "Mi Note 10 Lite",
   "brand": "Xiaomi",
   "codename": "toco",
   "xda_thread": "https://forum.xda-developers.com/t/rom-11-toco-official-dotos-v5-0-1.4235853/",
   "builds": {
      "gapps": [
         {
            "datetime": "1622239659",
            "filename": "dotOS-R-v5.1-toco-GAPPS-20210528-2200.zip",
            "id": "a626ab3df85c9486baee13bcd4ce6564",
            "romtype": "GAPPS",
            "size": "1517296564",
            "url": "https://downloads.droidontime.com/dot11/toco/gapps/dotOS-R-v5.1-toco-GAPPS-20210528-2200.zip",
            "version": "v5.1"
         }
      ],
      "vanilla": [
         {
            "datetime": "1622238008",
            "filename": "dotOS-R-v5.1-toco-OFFICIAL-20210528-2100.zip",
            "id": "aca9384f3d1fb658abf4719ab3c7e54a",
            "romtype": "OFFICIAL",
            "size": "1099212528",
            "url": "https://downloads.droidontime.com/dot11/toco/vanilla/dotOS-R-v5.1-toco-OFFICIAL-20210528-2100.zip",
            "version": "v5.1"
         }
      ]
   },
   "maintainers": [
      {
         "_id": "AndroidHQ254",
         "name": "Dennis Murimi",
         "url": "https://github.com/AndroidHQ254/"
      }
   ]
}
